odoo/addons/pos_eater/README.rst
odoo/addons/pos_eater/__init__.py
odoo/addons/pos_eater/__manifest__.py
odoo/addons/pos_eater/i18n/beesdoo_pos.pot
odoo/addons/pos_eater/i18n/pos_eater.pot
odoo/addons/pos_eater/models/__init__.py
odoo/addons/pos_eater/models/res_partner.py
odoo/addons/pos_eater/readme/CONTRIBUTORS.rst
odoo/addons/pos_eater/readme/DESCRIPTION.rst
odoo/addons/pos_eater/static/description/index.html
odoo/addons/pos_eater/static/src/js/screens.js
odoo/addons/pos_eater/static/src/xml/templates.xml
odoo/addons/pos_eater/views/assets.xml
odoo12_addon_pos_eater-12.0.2.0.0.dist-info/METADATA
odoo12_addon_pos_eater-12.0.2.0.0.dist-info/WHEEL
odoo12_addon_pos_eater-12.0.2.0.0.dist-info/top_level.txt
odoo12_addon_pos_eater-12.0.2.0.0.dist-info/RECORD
